cloud_auth_pkcs/__init__.py
cloud_auth_pkcs/base.py
cloud_auth_pkcs/aws/__init__.py
cloud_auth_pkcs/aws/awscredentials.py
cloud_auth_pkcs/aws/awshmaccredentials.py
cloud_auth_pkcs/azure/__init__.py
cloud_auth_pkcs/azure/azurecredentials.py
cloud_auth_pkcs/gcp/__init__.py
cloud_auth_pkcs/gcp/gcpcredentials.py
cloud_auth_pkcs-0.0.21.dist-info/licenses/LICENSE
testing/__init__.py
testing/test_all.py
testing/utils.py
cloud_auth_pkcs-0.0.21.dist-info/METADATA
cloud_auth_pkcs-0.0.21.dist-info/WHEEL
cloud_auth_pkcs-0.0.21.dist-info/top_level.txt
cloud_auth_pkcs-0.0.21.dist-info/RECORD
