Metadata-Version: 2.4
Name: cloud_auth_pkcs
Version: 0.0.21
Summary: Python PKCS-11 based Credentials provider for AWS, Azure and GCP
Home-page: https://github.com/salrashid123/cloud_auth_pkcs
Author: Sal Rashid
Author-email: salrashid123@gmail.com
Classifier: License :: OSI Approved :: Apache Software License
Classifier: Operating System :: OS Independent
Classifier: Development Status :: 3 - Alpha
Classifier: Intended Audience :: Developers
Classifier: Programming Language :: Python
Classifier: Programming Language :: Python :: 3.0
Classifier: Topic :: Software Development :: Libraries
Classifier: Topic :: Software Development :: Libraries :: Python Modules
License-File: LICENSE
Requires-Dist: python-pkcs11>=0.9.0
Requires-Dist: cryptography
Requires-Dist: requests
Provides-Extra: gcp
Requires-Dist: google-auth>=2.34.0; extra == "gcp"
Provides-Extra: aws
Requires-Dist: boto3; extra == "aws"
Requires-Dist: botocore; extra == "aws"
Provides-Extra: azure
Requires-Dist: azure-identity; extra == "azure"
Requires-Dist: azure-core; extra == "azure"
Dynamic: author
Dynamic: author-email
Dynamic: classifier
Dynamic: description
Dynamic: description-content-type
Dynamic: home-page
Dynamic: license-file
Dynamic: provides-extra
Dynamic: requires-dist
Dynamic: summary
